scppin/__init__.py
scppin/analyzer.py
scppin/graph.py
scppin/module.py
scppin/pvalues.py
scppin/core/__init__.py
scppin/core/bum_model.py
scppin/core/edge_weights.py
scppin/core/network_utils.py
scppin/core/pcst_solver.py
scppin/core/scoring.py
scppin/visualization/__init__.py
scppin/visualization/plotting.py
scppin-0.3.1.dist-info/licenses/LICENSE
scppin-0.3.1.dist-info/METADATA
scppin-0.3.1.dist-info/WHEEL
scppin-0.3.1.dist-info/top_level.txt
scppin-0.3.1.dist-info/RECORD
