Metadata-Version: 2.4
Name: scppin
Version: 0.3.1
Summary: Single-cell Protein-Protein Interaction Network Analysis
Author: Shahroze Abbas
License: GPL-3.0
Project-URL: Homepage, https://github.com/shahrozeabbas/scppin-py
Project-URL: Documentation, https://scppin-py.readthedocs.io
Project-URL: Repository, https://github.com/shahrozeabbas/scppin-py
Keywords: single-cell,protein-protein interaction,network analysis,bioinformatics
Classifier: Development Status :: 4 - Beta
Classifier: Intended Audience :: Science/Research
Classifier: License :: OSI Approved :: GNU General Public License v3 (GPLv3)
Classifier: Programming Language :: Python :: 3
Classifier: Programming Language :: Python :: 3.10
Classifier: Programming Language :: Python :: 3.11
Classifier: Programming Language :: Python :: 3.12
Classifier: Topic :: Scientific/Engineering :: Bio-Informatics
Requires-Python: >=3.10
License-File: LICENSE
Requires-Dist: numpy<2.0,>=1.20.0
Requires-Dist: scipy>=1.7.0
Requires-Dist: igraph>=0.11.0
Requires-Dist: matplotlib>=3.3.0
Requires-Dist: pandas>=1.3.0
Requires-Dist: pcst-fast>=1.0.0
Provides-Extra: scanpy
Requires-Dist: scanpy>=1.8.0; extra == "scanpy"
Requires-Dist: anndata>=0.8.0; extra == "scanpy"
Provides-Extra: dev
Requires-Dist: pytest>=7.0.0; extra == "dev"
Requires-Dist: pytest-cov>=3.0.0; extra == "dev"
Requires-Dist: black>=22.0.0; extra == "dev"
Requires-Dist: flake8>=4.0.0; extra == "dev"
Requires-Dist: mypy>=0.950; extra == "dev"
Provides-Extra: docs
Requires-Dist: sphinx>=5.0.0; extra == "docs"
Requires-Dist: furo>=2023.0.0; extra == "docs"
Requires-Dist: sphinx-autodoc-typehints>=1.23.0; extra == "docs"
Requires-Dist: sphinx-copybutton>=0.5.0; extra == "docs"
Requires-Dist: myst-parser>=1.0.0; extra == "docs"
Provides-Extra: all
Requires-Dist: scppin[dev,docs,scanpy]; extra == "all"
Dynamic: license-file
